ggstats/__init__.py
ggstats/ggstats.py
ggstats-0.1.2.dist-info/LICENCE
ggstats-0.1.2.dist-info/METADATA
ggstats-0.1.2.dist-info/WHEEL
ggstats-0.1.2.dist-info/top_level.txt
ggstats-0.1.2.dist-info/RECORD
