Metadata-Version: 2.1
Name: ggstats
Version: 0.1.2
Summary: A package for evaluating model performance metrics
Home-page: https://github.com/visit-www/ggstats.git
Author: Gaurav G
Author-email: lotusheart2016@gmail.com
Classifier: Programming Language :: Python :: 3
Classifier: License :: OSI Approved :: MIT License
Classifier: Operating System :: OS Independent
Requires-Python: >=3.6
License-File: LICENCE
Requires-Dist: pandas >=1.0.0
Requires-Dist: numpy >=1.18.0
